LICENSE
README.md
setup.cfg
setup.py
bin/grn-run
bin/grn-start
gpu_resource_negotiator.egg-info/PKG-INFO
gpu_resource_negotiator.egg-info/SOURCES.txt
gpu_resource_negotiator.egg-info/dependency_links.txt
gpu_resource_negotiator.egg-info/requires.txt
gpu_resource_negotiator.egg-info/top_level.txt
grn/__init__.py
grn/core/__init__.py
grn/core/constants.py
grn/core/globals.py
grn/core/gpu_master.py
grn/core/job.py
grn/grpc_resources/__init__.py
grn/grpc_resources/master_pb2.py
grn/grpc_resources/master_pb2_grpc.py
grn/utils/__init__.py
grn/utils/gpu_monitors.py
grn/utils/utils.py